eunomia_langchain/__init__.py
eunomia_langchain/document_loader.py
eunomia_langchain/retriever.py
eunomia_langchain-0.3.10.dist-info/METADATA
eunomia_langchain-0.3.10.dist-info/WHEEL
eunomia_langchain-0.3.10.dist-info/RECORD
